[
    {
        "id": 1,
        "name": "Coca-cola Zero | blik",
        "price": "7,50",
        "unit": "cl",
        "weight": "33",
        "unitprice": "1,51",
        "unitamount": "l",
        "description": "Serveren. Koud opdienen met een schijfje limoen. Bewaren. Bewaar koud in de koelkast. Gelieve te recycleren.",
        "amount": "15",
        "image" : "cola.jpg",
        "latitude" : "50.8065593",
        "longitude" : "3.3375152",
        "color": "Colors.green",
        "ail" : "Drank",
        "plank": "1"
    },
    {
        "id": 2,
        "name": "Fanta Orange | blik",
        "price": "7,50",
        "unit": "cl",
        "weight": "33",
        "unitprice": "1,51",
        "unitamount": "l",
        "description": "Serveren. Koud opdienen met een schijfje limoen. Bewaren. Bewaar koud in de koelkast. Gelieve te recycleren.",
        "amount": "15",
        "image" : "fanta.jpg",
        "latitude" : "50.8065593",
        "longitude" : "3.3375152",
        "color": "Colors.green",
        "ail" : "Drank",
        "plank": "1"
    },
    {
        "id": 3,
        "name": "Coca-cola Original | blik",
        "price": "7,50",
        "unit": "cl",
        "weight": "33",
        "unitprice": "1,51",
        "unitamount": "l",
        "description": "Serveren. Koud opdienen met een schijfje limoen. Bewaren. Bewaar koud in de koelkast. Gelieve te recycleren.",
        "amount": "15",
        "image" : "cola-original.jpg",
        "latitude" : "50.8065593",
        "longitude" : "3.3375152",
        "color": "Colors.green",
        "ail" : "Drank",
        "plank": "1"
    },
    {
        "id": 4,
        "name": "Doperwten | Hak | Bokaal",
        "price": "1,49",
        "unit": "gr",
        "weight": "230",
        "unitprice": "6,48",
        "unitamount": "kg",
        "description": "Groentenconserve | Erwten | Extra fijn | 350g Hak doperwtjes extra fijn.",
        "amount": "1",
        "image" : "doperwten-hak.jpg",
        "latitude" : "50.8065844",
        "longitude" : "3.3375205",
        "color": "Colors.green",
        "ail" : "Conserven",
        "plank": "2"
    },
    {
        "id": 5,
        "name": "Krieltjes",
        "price": "0,99",
        "unit": "g",
        "weight": "500",
        "unitprice": "2,50",
        "unitamount": "kg",
        "description": "Gekookte kriel aardappeltjes. Lekker in salades, perfect om te bakken en ook een lekkere koude snack.",
        "amount": "1",
        "image" : "krieltjes.jpg",
        "latitude" : "50.8065806",
        "longitude" : "3.3375515",
        "color": "Colors.green",
        "ail" : "Frigo inkom",
        "plank": "5"
    },
    {
        "id": 6,
        "name": "Margherita Classica Dunne korst| Dr. Oetker ",
        "price": "1,75",
        "unit": "g",
        "weight": "265",
        "unitprice": "6,60",
        "unitamount": "kg",
        "description": "Pizza | Margherita con basilico |Pizza fijne bodem met tomaten, mozzarella, olijfolie extra vergine en basilicum.",
        "amount": "1",
        "image" : "margherita-oetker.jpg",
        "latitude" : "50.8065648",
        "longitude" : "3.3376004",
        "color": "Colors.green",
        "ail" : "Diepvries",
        "plank": "1"
    },
    {
        "id": 7,
        "name": "Lay's Grills",
        "price": "1,19",
        "unit": "g",
        "weight": "125",
        "unitprice": "9,52",
        "unitamount": "kg",
        "description": "Maïs- en aardappelzoutje met baconsmaak. Gebakken in palmolie en in koolzaadolie",
        "amount": "1",
        "image" : "grills.jpg",
        "latitude" : "50.8065607",
        "longitude" : "3.3375852",
        "color": "Colors.green",
        "ail" : "Chips en wijnen",
        "plank": "4"
    },
    {
      "id": 8,
      "name": "Duyvis Crac-A-Nut | Barbecue",
      "price": "1,69",
      "unit": "g",
      "weight": "200",
      "unitprice": "8,45",
      "unitamount": "kg",
      "description": "Pinda's in een krokant jasje met barbecuesmaak.. Gebakken in zonnebloemolie",
      "amount": "1",
      "image" : "duyvis-bbq.jpg",
      "latitude" : "50.8065491",
      "longitude" : "3.3375917",
      "color": "Colors.green",
      "ail" : "Chips en wijnen",
      "plank": "3"
    }
]
